blazing_fast_ranking_metrics/__init__.py
blazing_fast_ranking_metrics-0.1.0.dist-info/WHEEL
blazing_fast_ranking_metrics-0.1.0.dist-info/METADATA
blazing_fast_ranking_metrics-0.1.0.dist-info/RECORD
