Metadata-Version: 2.1
Name: blazing-fast-ranking-metrics
Version: 0.1.0
Summary: 
Author: mmarin
Author-email: mikhail.marin@sbermarket.ru
Requires-Python: >=3.9,<4.0
Classifier: Programming Language :: Python :: 3
Classifier: Programming Language :: Python :: 3.10
Classifier: Programming Language :: Python :: 3.9
Requires-Dist: numpy (>=1.24.2,<2.0.0)
Requires-Dist: pandas (>=1.5.3,<2.0.0)
Requires-Dist: polars (>=0.16.8,<0.17.0)
